zope.schemaevent-0.3-py3.5-nspkg.pth
zope/schemaevent/__init__.py
zope/schemaevent/configure.zcml
zope/schemaevent/fieldevent.py
zope/schemaevent/testing.py
zope/schemaevent/tests/__init__.py
zope/schemaevent/tests/test_fieldevent.py
zope.schemaevent-0.3.dist-info/DESCRIPTION.rst
zope.schemaevent-0.3.dist-info/METADATA
zope.schemaevent-0.3.dist-info/RECORD
zope.schemaevent-0.3.dist-info/WHEEL
zope.schemaevent-0.3.dist-info/metadata.json
zope.schemaevent-0.3.dist-info/namespace_packages.txt
zope.schemaevent-0.3.dist-info/top_level.txt
