Metadata-Version: 2.0
Name: zope.schemaevent
Version: 0.3
Summary: Event subscribers for zope.schema
Home-page: https://github.com/zopefoundation/zope.schemaevent
Author: Jean-Francois Roche
Author-email: jfroche@affinitic.be
License: gpl
Keywords: zope schema event
Platform: UNKNOWN
Classifier: Development Status :: 5 - Production/Stable
Classifier: Intended Audience :: Developers
Classifier: Operating System :: OS Independent
Classifier: Programming Language :: Python
Classifier: Programming Language :: Python :: 2
Classifier: Programming Language :: Python :: 2.7
Classifier: Programming Language :: Python :: 3
Classifier: Programming Language :: Python :: 3.4
Classifier: Programming Language :: Python :: 3.5
Classifier: Programming Language :: Python :: 3.6
Classifier: Programming Language :: Python :: Implementation :: CPython
Classifier: Programming Language :: Python :: Implementation :: PyPy
Classifier: Framework :: Zope3
Classifier: Topic :: Software Development :: Libraries :: Python Modules
Requires-Dist: setuptools
Requires-Dist: zope.component
Requires-Dist: zope.schema
Provides-Extra: test
Requires-Dist: zope.configuration; extra == 'test'
Requires-Dist: zope.testing; extra == 'test'
Requires-Dist: zope.testrunner; extra == 'test'
